LICENSE.txt
MANIFEST.in
README
setup.py
automata/Makefile
automata/VM.py
automata/__init__.py
automata/automata.py
automata/avm.py
automata/avmjit.cc
automata/avmruntime.c
automata/avmruntime.h
automata/fuzzystring.py
automata/peid.py
automata/util.py
automata.egg-info/PKG-INFO
automata.egg-info/SOURCES.txt
automata.egg-info/dependency_links.txt
automata.egg-info/not-zip-safe
automata.egg-info/requires.txt
automata.egg-info/top_level.txt