Metadata-Version: 1.1
Name: automata
Version: 0.1.4
Summary: finite automata for python
Home-page: http://github.com/bniemczyk/automata
Author: Brandon Niemczyk
Author-email: brandon.niemczyk@gmail.com
License: BSD
Platform: UNKNOWN
Classifier: Development Status :: 3 - Alpha
Classifier: Intended Audience :: Developers
Classifier: Intended Audience :: Science/Research
Classifier: License :: OSI Approved :: BSD License
Classifier: Topic :: Scientific/Engineering :: Mathematics
